{
  "schemaVersion": 1,
  "id": "better_mod_button",
  "version": "${version}",
  "name": "Better Mod Button",
  "description": "Fixes the location of ModMenu's Mod Button",
  "authors": [
    "Minenash"
  ],
  "contact": {},
  "license": "MIT",
  "icon": "assets/starry/icon.png",
  "environment": "client",
  "entrypoints": {
    "client": [
      "starry.Initialization"
    ]
  },
  "mixins": [
    "mixins.json"
  ],
  "depends": {
    "fabricloader": ">=0.18.4",
    "fabric-api": "*",
    "minecraft": "~1.21.11",
    "java": ">=21"
  }
}
